armaclass/__init__.py
armaclass/arma_generator.py
armaclass/generator.py
armaclass/parser.py
armaclass-0.2.2.dist-info/LICENSE
armaclass-0.2.2.dist-info/METADATA
armaclass-0.2.2.dist-info/WHEEL
armaclass-0.2.2.dist-info/top_level.txt
armaclass-0.2.2.dist-info/RECORD
