Metadata-Version: 2.1
Name: armaclass
Version: 0.2.2
Summary: Python parser and generator for Arma class definitions (e.g. sqm files)
Home-page: https://github.com/overfl0/Armaclass
Author: Lukasz Taczuk
Author-email: 
License: MIT
Keywords: arma pbo sqm class parser generator
Classifier: Development Status :: 4 - Beta
Classifier: Intended Audience :: Developers
Classifier: Topic :: Software Development :: Build Tools
Classifier: Programming Language :: Python :: 3
Classifier: Programming Language :: Python :: 3.5
Classifier: Programming Language :: Python :: 3.6
Classifier: Programming Language :: Python :: 3.7
Classifier: Programming Language :: Python :: 3.8
Classifier: Programming Language :: Python :: 3.9
Classifier: License :: OSI Approved :: MIT License
License-File: LICENSE
